odoo/addons/partner_store/README.rst
odoo/addons/partner_store/__init__.py
odoo/addons/partner_store/__manifest__.py
odoo/addons/partner_store/i18n/it.po
odoo/addons/partner_store/i18n/partner_store.pot
odoo/addons/partner_store/models/__init__.py
odoo/addons/partner_store/models/res_partner.py
odoo/addons/partner_store/readme/CONFIGURATION.rst
odoo/addons/partner_store/readme/CONTRIBUTORS.md
odoo/addons/partner_store/readme/DESCRIPTION.md
odoo/addons/partner_store/readme/USAGE.md
odoo/addons/partner_store/static/description/icon.png
odoo/addons/partner_store/static/description/index.html
odoo/addons/partner_store/static/img/store.png
odoo/addons/partner_store/tests/__init__.py
odoo/addons/partner_store/tests/test_res_partner.py
odoo_addon_partner_store-17.0.1.0.0.2.dist-info/METADATA
odoo_addon_partner_store-17.0.1.0.0.2.dist-info/WHEEL
odoo_addon_partner_store-17.0.1.0.0.2.dist-info/top_level.txt
odoo_addon_partner_store-17.0.1.0.0.2.dist-info/RECORD
